{"id":"8c66af83-1406-417c-ad44-fa91ecab568d","shop":"candis-first-store.myshopify.com","state":"990136795186548","isOnline":true,"accessToken":"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","expires":"2021-08-23T21:52:36.750Z","scope":"write_products,write_customers,write_draft_orders,write_script_tags,write_themes","onlineAccessInfo":{"expires_in":86399,"associated_user_scope":"write_products,write_customers,write_draft_orders,write_script_tags,write_themes","session":"1dcdd52299bd96a0a776a28703cc8c5c9fc02b10d2e2aff0d40b94a1a9cc3701","account_number":0,"associated_user":{"id":75276288206,"first_name":"Candi","last_name":"Schoen","email":"candilw1@gmail.com","account_owner":true,"locale":"en","collaborator":false,"email_verified":true}}}